fancykimai/app.py
fancykimai/classes/click_groups.py
fancykimai/classes/kimai_types.py
fancykimai/commands/__init__.py
fancykimai/commands/activities.py
fancykimai/commands/config.py
fancykimai/commands/customers.py
fancykimai/commands/login.py
fancykimai/commands/projects.py
fancykimai/commands/teams.py
fancykimai/commands/timesheets.py
fancykimai/functions/activity.py
fancykimai/functions/config.py
fancykimai/functions/kimai.py
fancykimai/functions/project.py
fancykimai/functions/timesheets.py
fancykimai-0.1.10.dist-info/LICENSE
fancykimai-0.1.10.dist-info/METADATA
fancykimai-0.1.10.dist-info/WHEEL
fancykimai-0.1.10.dist-info/entry_points.txt
fancykimai-0.1.10.dist-info/RECORD
