Metadata-Version: 2.1
Name: fancykimai
Version: 0.1.10
Summary: CLI Interface to use with Kimai2
Home-page: https://fancywhale.ca
License: GPL-3.0
Keywords: kimai,cli,time-tracking
Author: Gui Martins
Author-email: gui.martins@fancywhale.ca
Requires-Python: >=3.11,<4.0
Classifier: License :: OSI Approved :: GNU General Public License v3 (GPLv3)
Classifier: Programming Language :: Python :: 3
Classifier: Programming Language :: Python :: 3.11
Requires-Dist: click-tester (>=1.0.0,<2.0.0)
Requires-Dist: iterfzf (>=1.2.0.46.1,<2.0.0.0.0)
Requires-Dist: keyring (>=24.3.1,<25.0.0)
Requires-Dist: pydantic (>=2.7.3,<3.0.0)
Requires-Dist: requests (>=2.31.0,<3.0.0)
Requires-Dist: rich (>=13.7.1,<14.0.0)
Project-URL: Repository, https://github.com/gcarrarom/FancyKimai
